_simple_build_system/__init__.py
_simple_build_system/_cli.py
_simple_build_system/_determine_version.py
_simple_build_system/_export_jsoncmds.py
_simple_build_system/_sphinxext.py
_simple_build_system/_sphinxutils.py
_simple_build_system/backend.py
_simple_build_system/build_summary.py
_simple_build_system/cfgbuilder.py
_simple_build_system/cfglocate.py
_simple_build_system/col.py
_simple_build_system/conf.py
_simple_build_system/cpudetect.py
_simple_build_system/db.py
_simple_build_system/dirs.py
_simple_build_system/dotgen.py
_simple_build_system/env.py
_simple_build_system/envcfg.py
_simple_build_system/envsetup.py
_simple_build_system/error.py
_simple_build_system/extdep_includemap.py
_simple_build_system/extractenv.py
_simple_build_system/find.py
_simple_build_system/findpkgdirs.py
_simple_build_system/formatlist.py
_simple_build_system/frontend.py
_simple_build_system/grep.py
_simple_build_system/incinfo.py
_simple_build_system/includes.py
_simple_build_system/init_project.py
_simple_build_system/instsl.py
_simple_build_system/instsl2.py
_simple_build_system/io.py
_simple_build_system/langs.py
_simple_build_system/loadpkgs.py
_simple_build_system/makefile.py
_simple_build_system/mtime.py
_simple_build_system/parse_args.py
_simple_build_system/pkgfilter.py
_simple_build_system/pkgutils.py
_simple_build_system/replace.py
_simple_build_system/singlecfg.py
_simple_build_system/target_base.py
_simple_build_system/target_builder.py
_simple_build_system/testlauncher.py
_simple_build_system/testxml.py
_simple_build_system/tfact_binary.py
_simple_build_system/tfact_headerdeps.py
_simple_build_system/tfact_libavail.py
_simple_build_system/tfact_prepinc.py
_simple_build_system/tfact_pyinit.py
_simple_build_system/tfact_reflogs.py
_simple_build_system/tfact_symlink.py
_simple_build_system/utils.py
_simple_build_system/data/cfgtemplate.txt
_simple_build_system/data/cmake/CMakeLists.txt
_simple_build_system/data/cmake/Detect.cmake
simple_build_system-1.7.2.dist-info/licenses/LICENSE
simple_build_system-1.7.2.dist-info/METADATA
simple_build_system-1.7.2.dist-info/WHEEL
simple_build_system-1.7.2.dist-info/entry_points.txt
simple_build_system-1.7.2.dist-info/top_level.txt
simple_build_system-1.7.2.dist-info/RECORD
