Metadata-Version: 2.4
Name: simple-build-system
Version: 1.7.2
Summary: A very simple to use build system for projects with primarily C++/Python code, intended for usage by scientific developers without a strong SW-engineering background.
Author-email: Thomas Kittelmann <thomas.kittelmann@ess.eu>
License:                                  Apache License
Project-URL: Homepage, https://mctools.github.io/simplebuild/
Project-URL: Bug Tracker, https://github.com/mctools/simplebuild/issues
Classifier: Programming Language :: Python :: 3
Classifier: License :: OSI Approved :: Apache Software License
Classifier: Operating System :: Unix
Requires-Python: >=3.8
License-File: LICENSE
Requires-Dist: tomli; python_version < "3.11"
Provides-Extra: all
Requires-Dist: pybind11>=2.10.4; extra == "all"
Requires-Dist: cmake>=3.24.2; extra == "all"
Dynamic: license-file
